MANIFEST.in
README.md
setup.cfg
setup.py
fiqs/__init__.py
fiqs/aggregations.py
fiqs/exceptions.py
fiqs/fields.py
fiqs/i18n.py
fiqs/models.py
fiqs/query.py
fiqs/tree.py
fiqs.egg-info/PKG-INFO
fiqs.egg-info/SOURCES.txt
fiqs.egg-info/dependency_links.txt
fiqs.egg-info/requires.txt
fiqs.egg-info/top_level.txt
fiqs/locale/fiqs.pot
fiqs/locale/fr/LC_MESSAGES/fiqs.mo
fiqs/locale/fr/LC_MESSAGES/fiqs.po
fiqs/locale/ja/LC_MESSAGES/fiqs.mo
fiqs/locale/ja/LC_MESSAGES/fiqs.po
fiqs/testing/__init__.py
fiqs/testing/gen_data.py
fiqs/testing/gen_sale_data.py
fiqs/testing/gen_traffic_data.py
fiqs/testing/models.py
fiqs/testing/utils.py
fiqs/tests/__init__.py
fiqs/tests/conftest.py
fiqs/tests/run_tests.py
fiqs/tests/test_aggregations.py
fiqs/tests/test_elasticsearch.py
fiqs/tests/test_fields.py
fiqs/tests/test_performance.py
fiqs/tests/test_query.py
fiqs/tests/test_tree.py