Metadata-Version: 1.0
Name: fiqs
Version: 0.3.34
Summary: Python client for Elasticsearch built on top of elasticsearch-dsl
Home-page: https://github.com/pmourlanne/fiqs
Author: Pierre Mourlanne
Author-email: pmourlanne@gmail.com
License: MIT License
Platform: UNKNOWN
